.gitignore
LICENSE
README.md
requirements.txt
setup.cfg
setup.py
REFPROPConnector/NIST2310.EXE
REFPROPConnector/__init__.py
REFPROPConnector/refprop_calculator.py
REFPROPConnector/refprop_pickable.py
REFPROPConnectorTest/__init__.py
REFPROPConnectorTest/test_dll_runtime.py
REFPROPConnectorTest/test_file.py
REFPROPConnectorTest/test_multiprocessing.py
REFPROPConnector/Handlers/__base_handler.py
REFPROPConnector/Handlers/__base_handler_picklable.py
REFPROPConnector/Handlers/__init__.py
REFPROPConnector/Handlers/__quality_iteration.py
REFPROPConnector/Handlers/__variable.py
REFPROPConnector/Handlers/coolprop_handler.py
REFPROPConnector/Handlers/refprop_handler.py
REFPROPConnector/Handlers/refprop_handler_picklable.py
REFPROPConnector/Handlers/Tools/__init__.py
REFPROPConnector/Handlers/Tools/refprop_plotter.py
REFPROPConnector/Handlers/Tools/units_converter.py
REFPROPConnector/Support/__init__.py
REFPROPConnector/Support/constants.py
REFPROPConnector/Support/refprop_names_tree.py
REFPROPConnector/Support/resources/REFPROP_exec.dat
REFPROPConnector/Support/resources/REFPROP_names.xml
REFPROPConnector/Support/resources/__init__.py
REFPROPConnector/Support/resources/file_handler.py
REFPROPConnector/Support/resources/rp_names_file_generator.py
REFPROP_connector.egg-info/PKG-INFO
REFPROP_connector.egg-info/SOURCES.txt
REFPROP_connector.egg-info/dependency_links.txt
REFPROP_connector.egg-info/requires.txt
REFPROP_connector.egg-info/top_level.txt
twine_upload/pip_upload.py