Metadata-Version: 2.1
Name: REFPROP-connector
Version: 0.4.1
Summary: Tools for launching REFPROP calculation and retrieving results from python
Home-page: https://www.dief.unifi.it/vp-177-serg-group-english-version.html
Author: Pietro Ungar
Author-email: pietro.ungar@unifi.it
License: GNU GPLv3
Download-URL: https://github.com/SERGGroup/REFPROPConnector/archive/refs/tags/0.4.1.tar.gz
Project-URL: Source, https://github.com/SERGGroup/REFPROPConnector
Project-URL: Tracker, https://github.com/SERGGroup/REFPROPConnector/issues
Platform: UNKNOWN
Classifier: Development Status :: 4 - Beta
Classifier: Intended Audience :: Science/Research
Classifier: Topic :: Scientific/Engineering
Classifier: License :: OSI Approved :: GNU General Public License v3 (GPLv3)
